image_processing/__init__.py
image_processing/combination.py
image_processing/transformation.py
utils/__init__.py
utils/io.py
utils/plot.py
IMAGE_PROCESSING_PACKPAGE-0.0.1.dist-info/METADATA
IMAGE_PROCESSING_PACKPAGE-0.0.1.dist-info/WHEEL
IMAGE_PROCESSING_PACKPAGE-0.0.1.dist-info/top_level.txt
IMAGE_PROCESSING_PACKPAGE-0.0.1.dist-info/RECORD
