Metadata-Version: 2.1
Name: IMAGE-PROCESSING-PACKPAGE
Version: 0.0.1
Summary: Image Processing Package using Skimage
Home-page: https://github.com/matheusmirandalacerda/IMAGE-PROCESSING-PACKPAGE
Author: Matheus
Requires-Python: >=3.8
Requires-Dist: matplotlib
Requires-Dist: numpy
Requires-Dist: scikit-image (>=0.16.1)
